apptk/__about__.py
apptk/__init__.py
apptk-0.0.0.dist-info/METADATA
apptk-0.0.0.dist-info/WHEEL
apptk-0.0.0.dist-info/licenses/LICENSE.txt
apptk-0.0.0.dist-info/RECORD
